carddavclient-0.1.dist-info/top_level.txt
carddavclient-0.1.dist-info/DESCRIPTION.rst
carddavclient-0.1.dist-info/metadata.json
carddavclient-0.1.dist-info/WHEEL
carddavclient-0.1.dist-info/RECORD
carddavclient-0.1.dist-info/METADATA
carddavclient/__main__.py
carddavclient/localcache.py
carddavclient/cmdline.py
carddavclient/addressbook.py
carddavclient/servercomm.py
carddavclient/config.py
carddavclient/__init__.py
carddavclient/tools.py
