Metadata-Version: 2.0
Name: carddavclient
Version: 0.1
Summary: Sync CardDAV ressources with local directory.
Home-page: UNKNOWN
Author: Jorispilot
Author-email: jorispilot@aquilenet.fr
License: MIT
Keywords: carddav,vcard
Platform: UNKNOWN
Classifier: Development Status :: 4 - Beta
Classifier: Environment :: Console
Classifier: Programming Language :: Python
Classifier: Programming Language :: Python :: 3 :: Only
Classifier: Topic :: Communications :: Email :: Address Book
